imagetitler/__init__.py
imagetitler/assets/fonts/BERNHC.TTF
imagetitler/assets/fonts/arial.ttf
imagetitler/assets/fonts/gadugi.ttf
imagetitler/assets/icons/the-renegade-coder-sample-icon.png
imagetitler/assets/icons/virtual-flat-sample-icon.png
imagetitler/assets/images/23-tech-topics-to-tackle.jpg
imagetitler/assets/images/baklava-in-every-language.jpg
imagetitler/assets/images/columbus-drivers-are-among-the-worst.jpg
imagetitler/assets/images/happy-new-year.jpg
imagetitler/assets/images/hello-world-in-c.jpg
imagetitler/assets/images/hello-world-in-matlab.jpg
imagetitler/assets/images/how-to-iterate-over-multiple-lists-at-the-same-time-in-python.jpg
imagetitler/assets/images/minimalism.jpg
imagetitler/assets/images/reflecting-on-my-third-semester-of-teaching.jpg
imagetitler/assets/images/the-art-of-simplification.jpg
imagetitler/assets/images/the-guide-to-causing-mass-panic.jpg
imagetitler/assets/images/welcome-to-the-image-titler-by-the-renegade-coder.jpg
imagetitler/constants.py
imagetitler/draw.py
imagetitler/parse.py
imagetitler/store.py
scripts/__init__.py
scripts/cli.py
scripts/gui.py
image_titler-2.5.1.dist-info/LICENSE
image_titler-2.5.1.dist-info/METADATA
image_titler-2.5.1.dist-info/WHEEL
image_titler-2.5.1.dist-info/entry_points.txt
image_titler-2.5.1.dist-info/RECORD
