Metadata-Version: 2.1
Name: image-titler
Version: 2.5.1
Summary: An image processing utility which provides options for generating thumbnails for various social media platforms.
Home-page: https://github.com/TheRenegadeCoder/image-titler
License: GPL-3.0-or-later
Author: Jeremy Grifski
Author-email: jeremy.grifski@therenegadecoder.com
Requires-Python: >=3.11,<4.0
Classifier: License :: OSI Approved :: GNU General Public License v3 or later (GPLv3+)
Classifier: Programming Language :: Python :: 3
Classifier: Programming Language :: Python :: 3.11
Classifier: Programming Language :: Python :: 3.12
Requires-Dist: matplotlib (>=3.0,<4.0)
Requires-Dist: pathvalidate (>=2.0,<3.0)
Requires-Dist: piexif (>=1.0,<2.0)
Requires-Dist: pillow (>=10.0.0,<11.0.0)
Requires-Dist: titlecase (>=2.0,<3.0)
Project-URL: Repository, https://github.com/TheRenegadeCoder/image-titler
